kulprit/__init__.py
kulprit/projector.py
kulprit/plots/__init__.py
kulprit/plots/plots.py
kulprit/projection/__init__.py
kulprit/projection/arviz_io.py
kulprit/projection/pymc_io.py
kulprit/projection/search_strategies.py
kulprit/projection/solver.py
kulprit-0.5.1.dist-info/licenses/LICENCE
kulprit-0.5.1.dist-info/WHEEL
kulprit-0.5.1.dist-info/METADATA
kulprit-0.5.1.dist-info/RECORD
