Metadata-Version: 2.4
Name: kulprit
Version: 0.5.1
Summary: Kullback-Leibler projections for Bayesian model selection.
Maintainer-email: Osvaldo Martin <aloctavodia@gmail.com>, Tomás Capretto <tomicapretto@gmail.com>
Classifier: Development Status :: 3 - Alpha
Classifier: Intended Audience :: Science/Research
Classifier: Intended Audience :: Education
Classifier: License :: OSI Approved :: MIT License
Classifier: Operating System :: OS Independent
Classifier: Programming Language :: Python
Classifier: Programming Language :: Python :: 3
Classifier: Programming Language :: Python :: 3.11
Classifier: Programming Language :: Python :: 3.12
Classifier: Programming Language :: Python :: 3.13
License-File: LICENCE
Requires-Dist: arviz_plots >=0.7.0
Requires-Dist: bambi >=0.16
Requires-Dist: scikit-learn>=1.0.2
Project-URL: source, https://github.com/bambinos/kulprit
Project-URL: tracker, https://github.com/bambinos/kulprit/issues
